<annotation>
	<folder>images</folder>
	<filename>codenames-cards.jpg</filename>
	<path>/Users/merrill/School/current/CS474/codenames-stuff/images/codenames-cards.jpg</path>
	<source>
		<database>Unknown</database>
	</source>
	<size>
		<width>2743</width>
		<height>1829</height>
		<depth>3</depth>
	</size>
	<segmented>0</segmented>
	<object>
		<name>A</name>
		<pose>Unspecified</pose>
		<truncated>0</truncated>
		<difficult>0</difficult>
		<bndbox>
			<xmin>1904</xmin>
			<ymin>291</ymin>
			<xmax>1935</xmax>
			<ymax>330</ymax>
		</bndbox>
	</object>
	<object>
		<name>A</name>
		<pose>Unspecified</pose>
		<truncated>0</truncated>
		<difficult>0</difficult>
		<bndbox>
			<xmin>307</xmin>
			<ymin>588</ymin>
			<xmax>335</xmax>
			<ymax>636</ymax>
		</bndbox>
	</object>
	<object>
		<name>A</name>
		<pose>Unspecified</pose>
		<truncated>0</truncated>
		<difficult>0</difficult>
		<bndbox>
			<xmin>1370</xmin>
			<ymin>580</ymin>
			<xmax>1401</xmax>
			<ymax>625</ymax>
		</bndbox>
	</object>
	<object>
		<name>A</name>
		<pose>Unspecified</pose>
		<truncated>0</truncated>
		<difficult>0</difficult>
		<bndbox>
			<xmin>1922</xmin>
			<ymin>567</ymin>
			<xmax>1951</xmax>
			<ymax>609</ymax>
		</bndbox>
	</object>
	<object>
		<name>A</name>
		<pose>Unspecified</pose>
		<truncated>0</truncated>
		<difficult>0</difficult>
		<bndbox>
			<xmin>2514</xmin>
			<ymin>575</ymin>
			<xmax>2549</xmax>
			<ymax>614</ymax>
		</bndbox>
	</object>
	<object>
		<name>A</name>
		<pose>Unspecified</pose>
		<truncated>0</truncated>
		<difficult>0</difficult>
		<bndbox>
			<xmin>1401</xmin>
			<ymin>951</ymin>
			<xmax>1433</xmax>
			<ymax>991</ymax>
		</bndbox>
	</object>
	<object>
		<name>A</name>
		<pose>Unspecified</pose>
		<truncated>0</truncated>
		<difficult>0</difficult>
		<bndbox>
			<xmin>2488</xmin>
			<ymin>851</ymin>
			<xmax>2522</xmax>
			<ymax>907</ymax>
		</bndbox>
	</object>
	<object>
		<name>A</name>
		<pose>Unspecified</pose>
		<truncated>0</truncated>
		<difficult>0</difficult>
		<bndbox>
			<xmin>2554</xmin>
			<ymin>1249</ymin>
			<xmax>2588</xmax>
			<ymax>1296</ymax>
		</bndbox>
	</object>
	<object>
		<name>A</name>
		<pose>Unspecified</pose>
		<truncated>0</truncated>
		<difficult>0</difficult>
		<bndbox>
			<xmin>2062</xmin>
			<ymin>1301</ymin>
			<xmax>2099</xmax>
			<ymax>1359</ymax>
		</bndbox>
	</object>
	<object>
		<name>A</name>
		<pose>Unspecified</pose>
		<truncated>0</truncated>
		<difficult>0</difficult>
		<bndbox>
			<xmin>770</xmin>
			<ymin>1330</ymin>
			<xmax>809</xmax>
			<ymax>1386</ymax>
		</bndbox>
	</object>
	<object>
		<name>A</name>
		<pose>Unspecified</pose>
		<truncated>0</truncated>
		<difficult>0</difficult>
		<bndbox>
			<xmin>1522</xmin>
			<ymin>1746</ymin>
			<xmax>1562</xmax>
			<ymax>1807</ymax>
		</bndbox>
	</object>
</annotation>
